reader/__init__.py
reader/__main__.py
reader/config.txt
reader/feed.py
reader/viewer.py
volha_reader-1.1.0.dist-info/METADATA
volha_reader-1.1.0.dist-info/WHEEL
volha_reader-1.1.0.dist-info/entry_points.txt
volha_reader-1.1.0.dist-info/top_level.txt
volha_reader-1.1.0.dist-info/RECORD
