Metadata-Version: 2.1
Name: volha-reader
Version: 1.1.0
Summary: Read the latest Real Python tutorials
Home-page: https://github.com/realpython/reader
Author: Real Python
Author-email: olga.bobarikina@gmail.com
License: MIT
Classifier: License :: OSI Approved :: MIT License
Classifier: Programming Language :: Python :: 3
Classifier: Programming Language :: Python :: 3.7
Requires-Dist: feedparser
Requires-Dist: html2text
